{
  "fetchedAtUTC": "2025-12-15T15:33:39.707Z",
  "fetchedAtLocal": "2025-12-16T00:33:39.706Z",
  "placeId": "ChIJ5aItaCPLA2ARI-sQQVyBvQs",
  "name": "関ヶ原 そば処幸山",
  "utcOffsetMinutes": 540,
  "today": {
    "gDay": 2,
    "slots": [
      {
        "start": "11:00",
        "end": "14:30"
      }
    ],
    "statusNow": "準備中",
    "isClosed": false
  },
  "tomorrow": {
    "gDay": 3,
    "slots": [
      {
        "start": "11:00",
        "end": "14:30"
      }
    ],
    "isClosed": false
  },
  "result": {
    "opening_hours": {
      "periods": [
        {
          "open": {
            "day": 0,
            "hour": 11,
            "minute": 0
          },
          "close": {
            "day": 0,
            "hour": 14,
            "minute": 30
          }
        },
        {
          "open": {
            "day": 0,
            "hour": 17,
            "minute": 0
          },
          "close": {
            "day": 0,
            "hour": 19,
            "minute": 30
          }
        },
        {
          "open": {
            "day": 2,
            "hour": 11,
            "minute": 0
          },
          "close": {
            "day": 2,
            "hour": 14,
            "minute": 30
          }
        },
        {
          "open": {
            "day": 3,
            "hour": 11,
            "minute": 0
          },
          "close": {
            "day": 3,
            "hour": 14,
            "minute": 30
          }
        },
        {
          "open": {
            "day": 4,
            "hour": 11,
            "minute": 0
          },
          "close": {
            "day": 4,
            "hour": 14,
            "minute": 30
          }
        },
        {
          "open": {
            "day": 5,
            "hour": 11,
            "minute": 0
          },
          "close": {
            "day": 5,
            "hour": 14,
            "minute": 30
          }
        },
        {
          "open": {
            "day": 6,
            "hour": 11,
            "minute": 0
          },
          "close": {
            "day": 6,
            "hour": 14,
            "minute": 30
          }
        },
        {
          "open": {
            "day": 6,
            "hour": 17,
            "minute": 0
          },
          "close": {
            "day": 6,
            "hour": 19,
            "minute": 30
          }
        }
      ]
    }
  }
}